topsis/__init__.py
topsis/topsis.py
Topsis_JagritGoyal_102217007-0.0.1.dist-info/LICENSE
Topsis_JagritGoyal_102217007-0.0.1.dist-info/METADATA
Topsis_JagritGoyal_102217007-0.0.1.dist-info/WHEEL
Topsis_JagritGoyal_102217007-0.0.1.dist-info/entry_points.txt
Topsis_JagritGoyal_102217007-0.0.1.dist-info/top_level.txt
Topsis_JagritGoyal_102217007-0.0.1.dist-info/RECORD
