Metadata-Version: 2.1
Name: Topsis_JagritGoyal_102217007
Version: 0.0.1
Summary: A Python package to perform TOPSIS (Technique for Order Preference by Similarity to Ideal Solution)
Home-page: https://github.com/jagrit-goyal/Topsis
Author: Jagrit Goyal
Author-email: jagritgoyal31@gmail.com
Classifier: Programming Language :: Python :: 3
Classifier: License :: OSI Approved :: MIT License
Classifier: Operating System :: OS Independent
Requires-Python: >=3.6
License-File: LICENSE
Requires-Dist: numpy
Requires-Dist: pandas
